astro_light_pollution/__init__.py
astro_light_pollution/__main__.py
astro_light_pollution/elevation.py
astro_light_pollution/main.py
astro_light_pollution/pollution.py
astro_light_pollution-0.1.0.dist-info/METADATA
astro_light_pollution-0.1.0.dist-info/WHEEL
astro_light_pollution-0.1.0.dist-info/entry_points.txt
astro_light_pollution-0.1.0.dist-info/RECORD
