Metadata-Version: 2.4
Name: astro_light_pollution
Version: 0.1.0
Summary: Geospatial and astronomy observation tools for AI assistants via MCP protocol
Project-URL: Homepage, https://github.com/yourusername/geospatial-astronomy-mcp
Project-URL: Documentation, https://github.com/yourusername/geospatial-astronomy-mcp#readme
Project-URL: Repository, https://github.com/yourusername/geospatial-astronomy-mcp.git
Project-URL: Bug Tracker, https://github.com/yourusername/geospatial-astronomy-mcp/issues
Author-email: Your Name <your.email@example.com>
License-Expression: MIT
Keywords: astronomy,elevation,fastmcp,geospatial,light-pollution,mcp
Classifier: Development Status :: 4 - Beta
Classifier: Intended Audience :: Science/Research
Classifier: License :: OSI Approved :: MIT License
Classifier: Programming Language :: Python :: 3
Classifier: Programming Language :: Python :: 3.12
Classifier: Programming Language :: Python :: 3.13
Classifier: Topic :: Scientific/Engineering :: Astronomy
Classifier: Topic :: Scientific/Engineering :: GIS
Requires-Python: >=3.12
Requires-Dist: aiohttp>=3.13.0
Requires-Dist: fastmcp>=2.12.4
Requires-Dist: pydantic>=2.12.2
Requires-Dist: requests>=2.32.5
Requires-Dist: selenium>=4.36.0
Provides-Extra: dev
Requires-Dist: black>=23.0.0; extra == 'dev'
Requires-Dist: pre-commit>=3.5.0; extra == 'dev'
Requires-Dist: pytest-asyncio>=0.21.0; extra == 'dev'
Requires-Dist: pytest>=7.4.0; extra == 'dev'
Requires-Dist: ruff>=0.1.0; extra == 'dev'
